LICENSE
MANIFEST.in
README.md
setup.py
schroot/__init__.py
schroot/chroot.py
schroot/core.py
schroot/errors.py
schroot/utils.py
schroot.egg-info/PKG-INFO
schroot.egg-info/SOURCES.txt
schroot.egg-info/dependency_links.txt
schroot.egg-info/top_level.txt