Metadata-Version: 1.0
Name: schroot
Version: 0.4
Summary: schroot chroot schroots!
Home-page: http://pault.ag/
Author: Paul Tagliamonte
Author-email: tag@pault.ag
License: Expat
Platform: any
